smwu_compiler/__init__.py
smwu_compiler/__main__.py
smwu_compiler-0.1.1.dist-info/METADATA
smwu_compiler-0.1.1.dist-info/WHEEL
smwu_compiler-0.1.1.dist-info/entry_points.txt
smwu_compiler-0.1.1.dist-info/top_level.txt
smwu_compiler-0.1.1.dist-info/RECORD
