Metadata-Version: 2.4
Name: smwu-compiler
Version: 0.1.1
Summary: Compare input file to answer.txt(or another input file) and show differences
Author: Yoon SeoJin
License: MIT
Classifier: Programming Language :: Python :: 3
Classifier: Operating System :: OS Independent
Requires-Python: >=3.6
